mintutils/__init__.py
mintutils/apps.py
mintutils/install_apps.py
mintutils-0.0.5.dist-info/LICENSE
mintutils-0.0.5.dist-info/METADATA
mintutils-0.0.5.dist-info/WHEEL
mintutils-0.0.5.dist-info/entry_points.txt
mintutils-0.0.5.dist-info/top_level.txt
mintutils-0.0.5.dist-info/RECORD
